{"_default": {"1": {"label": "\u00eele", "lem": "", "tags": "N+z1:fs", "flexional": ["fs"], "gram": "N", "semantic": ["z1"]}, "2": {"label": "\u00eele Maurice", "lem": "", "tags": "N+NN+Conc+z1:fs", "flexional": ["fs"], "gram": "N", "semantic": ["NN", "Conc", "z1"]}, "3": {"label": "\u00eele Saint-Louis", "lem": "", "tags": "N+NXN+Conc:fs", "flexional": ["fs"], "gram": "N", "semantic": ["NXN", "Conc"]}, "4": {"label": "\u00eele artificielle", "lem": "", "tags": "N+NA+Conc+z2:fs", "flexional": ["fs"], "gram": "N", "semantic": ["NA", "Conc", "z2"]}, "5": {"label": "\u00eele battue par les vents", "lem": "", "tags": "N+NAPN+Conc:fs", "flexional": ["fs"], "gram": "N", "semantic": ["NAPN", "Conc"]}, "6": {"label": "\u00eele c\u00f4ti\u00e8re", "lem": "", "tags": "N+NA+Conc:fs", "flexional": ["fs"], "gram": "N", "semantic": ["NA", "Conc"]}, "7": {"label": "\u00eele d'Ol\u00e9ron", "lem": "", "tags": "N+NDN+Conc:fs", "flexional": ["fs"], "gram": "N", "semantic": ["NDN", "Conc"]}, "8": {"label": "\u00eele de Bali", "lem": "", "tags": "N+NDN+Conc:fs", "flexional": ["fs"], "gram": "N", "semantic": ["NDN", "Conc"]}, "9": {"label": "\u00eele de Beaut\u00e9", "lem": "", "tags": "N+NDN+Conc:fs", "flexional": ["fs"], "gram": "N", "semantic": ["NDN", "Conc"]}, "10": {"label": "\u00eele de Born\u00e9o", "lem": "", "tags": "N+NDN+Conc:fs", "flexional": ["fs"], "gram": "N", "semantic": ["NDN", "Conc"]}, "11": {"label": "\u00eele de Chypre", "lem": "", "tags": "N+NDN+Conc:fs", "flexional": ["fs"], "gram": "N", "semantic": ["NDN", "Conc"]}, "12": {"label": "\u00eele de Cr\u00e8te", "lem": "", "tags": "N+NDN+Conc:fs", "flexional": ["fs"], "gram": "N", "semantic": ["NDN", "Conc"]}, "13": {"label": "\u00eele de France", "lem": "", "tags": "N+NDN:fs", "flexional": ["fs"], "gram": "N", "semantic": ["NDN"]}, "14": {"label": "\u00eele de Java", "lem": "", "tags": "N+NDN+Conc:fs", "flexional": ["fs"], "gram": "N", "semantic": ["NDN", "Conc"]}, "15": {"label": "\u00eele de Mad\u00e8re", "lem": "", "tags": "N+NDN+Conc:fs", "flexional": ["fs"], "gram": "N", "semantic": ["NDN", "Conc"]}, "16": {"label": "\u00eele de P\u00e2ques", "lem": "", "tags": "N+NDN+Conc:fs", "flexional": ["fs"], "gram": "N", "semantic": ["NDN", "Conc"]}, "17": {"label": "\u00eele de Rhodes", "lem": "", "tags": "N+NDN+Conc:fs", "flexional": ["fs"], "gram": "N", "semantic": ["NDN", "Conc"]}, "18": {"label": "\u00eele de R\u00e9", "lem": "", "tags": "N+NDN+Conc:fs", "flexional": ["fs"], "gram": "N", "semantic": ["NDN", "Conc"]}, "19": {"label": "\u00eele de Sainte-H\u00e9l\u00e8ne", "lem": "", "tags": "N+NPAN+Conc:fs", "flexional": ["fs"], "gram": "N", "semantic": ["NPAN", "Conc"]}, "20": {"label": "\u00eele de Sumatra", "lem": "", "tags": "N+NDN+Conc:fs", "flexional": ["fs"], "gram": "N", "semantic": ["NDN", "Conc"]}, "21": {"label": "\u00eele de Ta\u00efwan", "lem": "", "tags": "N+NDN+Conc:fs", "flexional": ["fs"], "gram": "N", "semantic": ["NDN", "Conc"]}, "22": {"label": "\u00eele de Tobago", "lem": "", "tags": "N+NDN+Conc:fs", "flexional": ["fs"], "gram": "N", "semantic": ["NDN", "Conc"]}, "23": {"label": "\u00eele de la Barbade", "lem": "", "tags": "N+NDN+Conc:fs", "flexional": ["fs"], "gram": "N", "semantic": ["NDN", "Conc"]}, "24": {"label": "\u00eele de la Cit\u00e9", "lem": "", "tags": "N+NDN+Conc:fs", "flexional": ["fs"], "gram": "N", "semantic": ["NDN", "Conc"]}, "25": {"label": "\u00eele de la Guadeloupe", "lem": "", "tags": "N+NDN+Conc:fs", "flexional": ["fs"], "gram": "N", "semantic": ["NDN", "Conc"]}, "26": {"label": "\u00eele de la R\u00e9union", "lem": "", "tags": "N+NDN+Conc:fs", "flexional": ["fs"], "gram": "N", "semantic": ["NDN", "Conc"]}, "27": {"label": "\u00eele de la Tortue", "lem": "", "tags": "N+NDN+Conc:fs", "flexional": ["fs"], "gram": "N", "semantic": ["NDN", "Conc"]}, "28": {"label": "\u00eele de la Trinit\u00e9", "lem": "", "tags": "N+NDN+Conc:fs", "flexional": ["fs"], "gram": "N", "semantic": ["NDN", "Conc"]}, "29": {"label": "\u00eele du Diable", "lem": "", "tags": "N+NDN+Conc:fs", "flexional": ["fs"], "gram": "N", "semantic": ["NDN", "Conc"]}, "30": {"label": "\u00eele d\u00e9serte", "lem": "", "tags": "N+NA+Conc+z1:fs", "flexional": ["fs"], "gram": "N", "semantic": ["NA", "Conc", "z1"]}, "31": {"label": "\u00eele flottante", "lem": "", "tags": "N+NA+Conc+z2:fs", "flexional": ["fs"], "gram": "N", "semantic": ["NA", "Conc", "z2"]}, "32": {"label": "\u00eeles", "lem": "\u00eele", "tags": "N+z1:fp", "flexional": ["fp"], "gram": "N", "semantic": ["z1"]}, "33": {"label": "\u00eeles Al\u00e9outiennes", "lem": "", "tags": "N+NN+Conc+Conc:fp", "flexional": ["fp"], "gram": "N", "semantic": ["NN", "Conc", "Conc"]}, "34": {"label": "\u00eeles Australes", "lem": "", "tags": "N+NA+Conc:fp", "flexional": ["fp"], "gram": "N", "semantic": ["NA", "Conc"]}, "35": {"label": "\u00eeles Bahamas", "lem": "", "tags": "N+NN+Conc+z1:fp", "flexional": ["fp"], "gram": "N", "semantic": ["NN", "Conc", "z1"]}, "36": {"label": "\u00eeles Bal\u00e9ares", "lem": "", "tags": "N+NN+Conc+z1:fp", "flexional": ["fp"], "gram": "N", "semantic": ["NN", "Conc", "z1"]}, "37": {"label": "\u00eeles Britanniques", "lem": "", "tags": "N+NA+Conc:fp", "flexional": ["fp"], "gram": "N", "semantic": ["NA", "Conc"]}, "38": {"label": "\u00eeles Canaries", "lem": "", "tags": "N+NN+Conc+z1:fp", "flexional": ["fp"], "gram": "N", "semantic": ["NN", "Conc", "z1"]}, "39": {"label": "\u00eeles Ca\u00efmans", "lem": "", "tags": "N+NN+Conc:fp", "flexional": ["fp"], "gram": "N", "semantic": ["NN", "Conc"]}, "40": {"label": "\u00eeles Comores", "lem": "", "tags": "N+NN+Conc+z2:fp", "flexional": ["fp"], "gram": "N", "semantic": ["NN", "Conc", "z2"]}, "41": {"label": "\u00eeles Eoliennes", "lem": "", "tags": "N+NN+Conc:fp", "flexional": ["fp"], "gram": "N", "semantic": ["NN", "Conc"]}, "42": {"label": "\u00eeles Fortun\u00e9es", "lem": "", "tags": "N+NN+Conc:fp", "flexional": ["fp"], "gram": "N", "semantic": ["NN", "Conc"]}, "43": {"label": "\u00eeles F\u00e9ro\u00e9", "lem": "", "tags": "N+NN+Conc:fp", "flexional": ["fp"], "gram": "N", "semantic": ["NN", "Conc"]}, "44": {"label": "\u00eeles Galapagos", "lem": "", "tags": "N+NN+Conc+z1:fp", "flexional": ["fp"], "gram": "N", "semantic": ["NN", "Conc", "z1"]}, "45": {"label": "\u00eeles Glorieuses", "lem": "", "tags": "N+NN+Conc:fp", "flexional": ["fp"], "gram": "N", "semantic": ["NN", "Conc"]}, "46": {"label": "\u00eeles Hawa\u00ef", "lem": "", "tags": "N+NN+Conc+z1:fp", "flexional": ["fp"], "gram": "N", "semantic": ["NN", "Conc", "z1"]}, "47": {"label": "\u00eeles Ioniennes", "lem": "", "tags": "N+NN+Conc:fp", "flexional": ["fp"], "gram": "N", "semantic": ["NN", "Conc"]}, "48": {"label": "\u00eeles Kouriles", "lem": "", "tags": "N+NN+Conc:fp", "flexional": ["fp"], "gram": "N", "semantic": ["NN", "Conc"]}, "49": {"label": "\u00eeles Maldives", "lem": "", "tags": "N+NN+Conc+z1:fp", "flexional": ["fp"], "gram": "N", "semantic": ["NN", "Conc", "z1"]}, "50": {"label": "\u00eeles Malouines", "lem": "", "tags": "N+NN+Conc:fp", "flexional": ["fp"], "gram": "N", "semantic": ["NN", "Conc"]}, "51": {"label": "\u00eeles Marquises", "lem": "", "tags": "N+NN+Conc+z1:fp", "flexional": ["fp"], "gram": "N", "semantic": ["NN", "Conc", "z1"]}, "52": {"label": "\u00eeles Shetland", "lem": "", "tags": "N+NN+Conc:fp", "flexional": ["fp"], "gram": "N", "semantic": ["NN", "Conc"]}, "53": {"label": "\u00eeles Vierges", "lem": "", "tags": "N+NN+Conc:fp", "flexional": ["fp"], "gram": "N", "semantic": ["NN", "Conc"]}, "54": {"label": "\u00eeles anglo-normandes", "lem": "", "tags": "N+NXA+Conc:fp", "flexional": ["fp"], "gram": "N", "semantic": ["NXA", "Conc"]}, "55": {"label": "\u00eeles artificielles", "lem": "\u00eele artificielle", "tags": "N+NA+Conc+z2:fp", "flexional": ["fp"], "gram": "N", "semantic": ["NA", "Conc", "z2"]}, "56": {"label": "\u00eeles de la Sonde", "lem": "", "tags": "N+NDN+Conc:fp", "flexional": ["fp"], "gram": "N", "semantic": ["NDN", "Conc"]}, "57": {"label": "\u00eeles d\u00e9sertes", "lem": "\u00eele d\u00e9serte", "tags": "N+NA+Conc+z1:fp", "flexional": ["fp"], "gram": "N", "semantic": ["NA", "Conc", "z1"]}, "58": {"label": "\u00eeles madr\u00e9poriques", "lem": "\u00eele madr\u00e9porique", "tags": "N+NA+Conc:fp", "flexional": ["fp"], "gram": "N", "semantic": ["NA", "Conc"]}, "59": {"label": "\u00eeles sous le Vent", "lem": "", "tags": "N+NDN+Conc:fp", "flexional": ["fp"], "gram": "N", "semantic": ["NDN", "Conc"]}, "60": {"label": "\u00eelet", "lem": "", "tags": "N:ms", "flexional": ["ms"], "gram": "N", "semantic": []}, "61": {"label": "\u00eelets", "lem": "\u00eelet", "tags": "N:mp", "flexional": ["mp"], "gram": "N", "semantic": []}, "62": {"label": "\u00eelette", "lem": "", "tags": "N:fs", "flexional": ["fs"], "gram": "N", "semantic": []}, "63": {"label": "\u00eelettes", "lem": "\u00eelette", "tags": "N:fp", "flexional": ["fp"], "gram": "N", "semantic": []}, "64": {"label": "\u00eelien", "lem": "", "tags": "N+z2:ms", "flexional": ["ms"], "gram": "N", "semantic": ["z2"]}, "65": {"label": "\u00eelien", "lem": "", "tags": "A+z2:ms", "flexional": ["ms"], "gram": "A", "semantic": ["z2"]}, "66": {"label": "\u00eelienne", "lem": "\u00eelien", "tags": "N+z2:fs", "flexional": ["fs"], "gram": "N", "semantic": ["z2"]}, "67": {"label": "\u00eelienne", "lem": "\u00eelien", "tags": "A+z2:fs", "flexional": ["fs"], "gram": "A", "semantic": ["z2"]}, "68": {"label": "\u00eeliennes", "lem": "\u00eelien", "tags": "N+z2:fp", "flexional": ["fp"], "gram": "N", "semantic": ["z2"]}, "69": {"label": "\u00eeliennes", "lem": "\u00eelien", "tags": "A+z2:fp", "flexional": ["fp"], "gram": "A", "semantic": ["z2"]}, "70": {"label": "\u00eeliens", "lem": "\u00eelien", "tags": "N+z2:mp", "flexional": ["mp"], "gram": "N", "semantic": ["z2"]}, "71": {"label": "\u00eeliens", "lem": "\u00eelien", "tags": "A+z2:mp", "flexional": ["mp"], "gram": "A", "semantic": ["z2"]}, "72": {"label": "\u00eelot", "lem": "", "tags": "N+z1:ms", "flexional": ["ms"], "gram": "N", "semantic": ["z1"]}, "73": {"label": "\u00eelot de r\u00e9sistance", "lem": "", "tags": "N+NDN+HumColl:ms", "flexional": ["ms"], "gram": "N", "semantic": ["NDN", "HumColl"]}, "74": {"label": "\u00eelot nucl\u00e9aire", "lem": "", "tags": "N+NA+Conc:ms", "flexional": ["ms"], "gram": "N", "semantic": ["NA", "Conc"]}, "75": {"label": "\u00eelota", "lem": "\u00eeloter", "tags": "V+z2:J3s", "flexional": ["J3s"], "gram": "V", "semantic": ["z2"]}, "76": {"label": "\u00eelotage", "lem": "", "tags": "N+z2:ms", "flexional": ["ms"], "gram": "N", "semantic": ["z2"]}, "77": {"label": "\u00eelotages", "lem": "\u00eelotage", "tags": "N+z2:mp", "flexional": ["mp"], "gram": "N", "semantic": ["z2"]}, "78": {"label": "\u00eelotai", "lem": "\u00eeloter", "tags": "V+z2:J1s", "flexional": ["J1s"], "gram": "V", "semantic": ["z2"]}, "79": {"label": "\u00eelotaient", "lem": "\u00eeloter", "tags": "V+z2:I3p", "flexional": ["I3p"], "gram": "V", "semantic": ["z2"]}, "80": {"label": "\u00eelotais", "lem": "\u00eeloter", "tags": "V+z2:I1s:I2s", "flexional": ["I1s", "I2s"], "gram": "V", "semantic": ["z2"]}, "81": {"label": "\u00eelotait", "lem": "\u00eeloter", "tags": "V+z2:I3s", "flexional": ["I3s"], "gram": "V", "semantic": ["z2"]}, "82": {"label": "\u00eelotant", "lem": "\u00eeloter", "tags": "V+z2:G", "flexional": ["G"], "gram": "V", "semantic": ["z2"]}, "83": {"label": "\u00eelotas", "lem": "\u00eeloter", "tags": "V+z2:J2s", "flexional": ["J2s"], "gram": "V", "semantic": ["z2"]}, "84": {"label": "\u00eelotasse", "lem": "\u00eeloter", "tags": "V+z2:T1s", "flexional": ["T1s"], "gram": "V", "semantic": ["z2"]}, "85": {"label": "\u00eelotassent", "lem": "\u00eeloter", "tags": "V+z2:T3p", "flexional": ["T3p"], "gram": "V", "semantic": ["z2"]}, "86": {"label": "\u00eelotasses", "lem": "\u00eeloter", "tags": "V+z2:T2s", "flexional": ["T2s"], "gram": "V", "semantic": ["z2"]}, "87": {"label": "\u00eelotassiez", "lem": "\u00eeloter", "tags": "V+z2:T2p", "flexional": ["T2p"], "gram": "V", "semantic": ["z2"]}, "88": {"label": "\u00eelotassions", "lem": "\u00eeloter", "tags": "V+z2:T1p", "flexional": ["T1p"], "gram": "V", "semantic": ["z2"]}, "89": {"label": "\u00eelote", "lem": "\u00eeloter", "tags": "V+z2:P1s:P3s:S1s:S3s:Y2s", "flexional": ["P1s", "P3s", "S1s", "S3s", "Y2s"], "gram": "V", "semantic": ["z2"]}, "90": {"label": "\u00eelotent", "lem": "\u00eeloter", "tags": "V+z2:P3p:S3p", "flexional": ["P3p", "S3p"], "gram": "V", "semantic": ["z2"]}, "91": {"label": "\u00eeloter", "lem": "", "tags": "V+z2:W", "flexional": ["W"], "gram": "V", "semantic": ["z2"]}, "92": {"label": "\u00eelotera", "lem": "\u00eeloter", "tags": "V+z2:F3s", "flexional": ["F3s"], "gram": "V", "semantic": ["z2"]}, "93": {"label": "\u00eeloterai", "lem": "\u00eeloter", "tags": "V+z2:F1s", "flexional": ["F1s"], "gram": "V", "semantic": ["z2"]}, "94": {"label": "\u00eeloteraient", "lem": "\u00eeloter", "tags": "V+z2:C3p", "flexional": ["C3p"], "gram": "V", "semantic": ["z2"]}, "95": {"label": "\u00eeloterais", "lem": "\u00eeloter", "tags": "V+z2:C1s:C2s", "flexional": ["C1s", "C2s"], "gram": "V", "semantic": ["z2"]}, "96": {"label": "\u00eeloterait", "lem": "\u00eeloter", "tags": "V+z2:C3s", "flexional": ["C3s"], "gram": "V", "semantic": ["z2"]}, "97": {"label": "\u00eeloteras", "lem": "\u00eeloter", "tags": "V+z2:F2s", "flexional": ["F2s"], "gram": "V", "semantic": ["z2"]}, "98": {"label": "\u00eeloterez", "lem": "\u00eeloter", "tags": "V+z2:F2p", "flexional": ["F2p"], "gram": "V", "semantic": ["z2"]}, "99": {"label": "\u00eeloteriez", "lem": "\u00eeloter", "tags": "V+z2:C2p", "flexional": ["C2p"], "gram": "V", "semantic": ["z2"]}, "100": {"label": "\u00eeloterions", "lem": "\u00eeloter", "tags": "V+z2:C1p", "flexional": ["C1p"], "gram": "V", "semantic": ["z2"]}, "101": {"label": "\u00eeloterons", "lem": "\u00eeloter", "tags": "V+z2:F1p", "flexional": ["F1p"], "gram": "V", "semantic": ["z2"]}, "102": {"label": "\u00eeloteront", "lem": "\u00eeloter", "tags": "V+z2:F3p", "flexional": ["F3p"], "gram": "V", "semantic": ["z2"]}, "103": {"label": "\u00eelotes", "lem": "\u00eeloter", "tags": "V+z2:P2s:S2s", "flexional": ["P2s", "S2s"], "gram": "V", "semantic": ["z2"]}, "104": {"label": "\u00eelotez", "lem": "\u00eeloter", "tags": "V+z2:P2p:Y2p", "flexional": ["P2p", "Y2p"], "gram": "V", "semantic": ["z2"]}, "105": {"label": "\u00eelotier", "lem": "", "tags": "N+z2:ms", "flexional": ["ms"], "gram": "N", "semantic": ["z2"]}, "106": {"label": "\u00eelotiers", "lem": "\u00eelotier", "tags": "N+z2:mp", "flexional": ["mp"], "gram": "N", "semantic": ["z2"]}, "107": {"label": "\u00eelotiez", "lem": "\u00eeloter", "tags": "V+z2:I2p:S2p", "flexional": ["I2p", "S2p"], "gram": "V", "semantic": ["z2"]}, "108": {"label": "\u00eelotions", "lem": "\u00eeloter", "tags": "V+z2:I1p:S1p", "flexional": ["I1p", "S1p"], "gram": "V", "semantic": ["z2"]}, "109": {"label": "\u00eeloti\u00e8re", "lem": "\u00eelotier", "tags": "N+z2:fs", "flexional": ["fs"], "gram": "N", "semantic": ["z2"]}, "110": {"label": "\u00eeloti\u00e8res", "lem": "\u00eelotier", "tags": "N+z2:fp", "flexional": ["fp"], "gram": "N", "semantic": ["z2"]}, "111": {"label": "\u00eelotons", "lem": "\u00eeloter", "tags": "V+z2:P1p:Y1p", "flexional": ["P1p", "Y1p"], "gram": "V", "semantic": ["z2"]}, "112": {"label": "\u00eelots", "lem": "\u00eelot", "tags": "N+z1:mp", "flexional": ["mp"], "gram": "N", "semantic": ["z1"]}, "113": {"label": "\u00eelots directionnels", "lem": "\u00eelot directionnel", "tags": "N+NA+Conc:mp", "flexional": ["mp"], "gram": "N", "semantic": ["NA", "Conc"]}, "114": {"label": "\u00eelot\u00e2mes", "lem": "\u00eeloter", "tags": "V+z2:J1p", "flexional": ["J1p"], "gram": "V", "semantic": ["z2"]}, "115": {"label": "\u00eelot\u00e2t", "lem": "\u00eeloter", "tags": "V+z2:T3s", "flexional": ["T3s"], "gram": "V", "semantic": ["z2"]}, "116": {"label": "\u00eelot\u00e2tes", "lem": "\u00eeloter", "tags": "V+z2:J2p", "flexional": ["J2p"], "gram": "V", "semantic": ["z2"]}, "117": {"label": "\u00eelot\u00e8rent", "lem": "\u00eeloter", "tags": "V+z2:J3p", "flexional": ["J3p"], "gram": "V", "semantic": ["z2"]}, "118": {"label": "\u00eelot\u00e9", "lem": "\u00eeloter", "tags": "V+z2:Kms", "flexional": ["Kms"], "gram": "V", "semantic": ["z2"]}, "119": {"label": "\u00eelot\u00e9e", "lem": "\u00eeloter", "tags": "V+z2:Kfs", "flexional": ["Kfs"], "gram": "V", "semantic": ["z2"]}, "120": {"label": "\u00eelot\u00e9es", "lem": "\u00eeloter", "tags": "V+z2:Kfp", "flexional": ["Kfp"], "gram": "V", "semantic": ["z2"]}, "121": {"label": "\u00eelot\u00e9s", "lem": "\u00eeloter", "tags": "V+z2:Kmp", "flexional": ["Kmp"], "gram": "V", "semantic": ["z2"]}}}